export_and_plot/export.py
export_and_plot/plot.py
nanobio_core/.git
nanobio_core/.gitignore
nanobio_core/README.md
nanobio_core/epic_cardio/__init__.py
nanobio_core/epic_cardio/animation.py
nanobio_core/epic_cardio/cell_maxima.py
nanobio_core/epic_cardio/cell_selector.py
nanobio_core/epic_cardio/data_correction.py
nanobio_core/epic_cardio/defs.py
nanobio_core/epic_cardio/filter.py
nanobio_core/epic_cardio/math_ops.py
nanobio_core/epic_cardio/measurement_load.py
nanobio_core/epic_cardio/processing.py
nanobio_core/epic_cardio/tmp.py
nanobio_core/image_fitting/__init__.py
nanobio_core/image_fitting/cardio_mic.py
nanobio_core/image_fitting/funcs.py
nanobio_core/image_fitting/single_cell_evaluator.py
napari_cardio_bio_eval/__init__.py
napari_cardio_bio_eval/napari.yaml
napari_cardio_bio_eval/peak_detection_widget.py
napari_cardio_bio_eval/segmentation_widget.py
napari_cardio_bio_eval/widget_utils.py
napari_cardio_bio_eval/_tests/__init__.py
napari_cardio_bio_eval/_tests/test_widget.py
napari_cardio_bio_eval-0.1.5.dist-info/LICENSE
napari_cardio_bio_eval-0.1.5.dist-info/METADATA
napari_cardio_bio_eval-0.1.5.dist-info/WHEEL
napari_cardio_bio_eval-0.1.5.dist-info/entry_points.txt
napari_cardio_bio_eval-0.1.5.dist-info/top_level.txt
napari_cardio_bio_eval-0.1.5.dist-info/RECORD
