Metadata-Version: 2.1
Name: napari-cardio-bio-eval
Version: 0.1.5
Summary: The evaluation of the epic cardio biosensor integrated into napari
Author: Nanobiosensorics
Author-email: horvath.robert@energia.mta.hu
License: 
Classifier: Development Status :: 2 - Pre-Alpha
Classifier: Framework :: napari
Classifier: Intended Audience :: Developers
Classifier: License :: OSI Approved :: BSD License
Classifier: Operating System :: OS Independent
Classifier: Programming Language :: Python
Classifier: Programming Language :: Python :: 3
Classifier: Programming Language :: Python :: 3 :: Only
Classifier: Programming Language :: Python :: 3.10
Classifier: Programming Language :: Python :: 3.11
Classifier: Programming Language :: Python :: 3.12
Classifier: Topic :: Scientific/Engineering :: Image Processing
Requires-Python: >=3.10
License-File: LICENSE
Requires-Dist: matplotlib
Requires-Dist: opencv-python-headless
Requires-Dist: openpyxl
Requires-Dist: napari[pyqt5]
Requires-Dist: torch
Requires-Dist: numpy==1.26
Provides-Extra: testing
Requires-Dist: tox; extra == "testing"
Requires-Dist: pytest; extra == "testing"
Requires-Dist: pytest-cov; extra == "testing"
Requires-Dist: pytest-qt; extra == "testing"
Requires-Dist: napari; extra == "testing"
Requires-Dist: pyqt5; extra == "testing"
